modssc/__about__.py
modssc/__init__.py
modssc/__main__.py
modssc/device.py
modssc/logging.py
modssc/cli/__init__.py
modssc/cli/_utils.py
modssc/cli/app.py
modssc/cli/augmentation.py
modssc/cli/datasets.py
modssc/cli/evaluation.py
modssc/cli/graph.py
modssc/cli/inductive.py
modssc/cli/logging.py
modssc/cli/preprocess.py
modssc/cli/sampling.py
modssc/cli/supervised.py
modssc/cli/transductive.py
modssc/data_augmentation/__init__.py
modssc/data_augmentation/api.py
modssc/data_augmentation/errors.py
modssc/data_augmentation/optional.py
modssc/data_augmentation/plan.py
modssc/data_augmentation/registry.py
modssc/data_augmentation/types.py
modssc/data_augmentation/utils.py
modssc/data_augmentation/ops/__init__.py
modssc/data_augmentation/ops/audio.py
modssc/data_augmentation/ops/base.py
modssc/data_augmentation/ops/core.py
modssc/data_augmentation/ops/graph.py
modssc/data_augmentation/ops/tabular.py
modssc/data_augmentation/ops/text.py
modssc/data_augmentation/ops/vision.py
modssc/data_loader/__init__.py
modssc/data_loader/api.py
modssc/data_loader/cache.py
modssc/data_loader/errors.py
modssc/data_loader/formats.py
modssc/data_loader/manifest.py
modssc/data_loader/numpy_adapter.py
modssc/data_loader/optional.py
modssc/data_loader/types.py
modssc/data_loader/uri.py
modssc/data_loader/catalog/__init__.py
modssc/data_loader/catalog/audio.py
modssc/data_loader/catalog/graph.py
modssc/data_loader/catalog/tabular.py
modssc/data_loader/catalog/text.py
modssc/data_loader/catalog/toy.py
modssc/data_loader/catalog/vision.py
modssc/data_loader/providers/__init__.py
modssc/data_loader/providers/base.py
modssc/data_loader/providers/hf.py
modssc/data_loader/providers/openml.py
modssc/data_loader/providers/pyg.py
modssc/data_loader/providers/tfds.py
modssc/data_loader/providers/torchaudio.py
modssc/data_loader/providers/torchvision.py
modssc/data_loader/providers/toy.py
modssc/data_loader/storage/__init__.py
modssc/data_loader/storage/files.py
modssc/evaluation/__init__.py
modssc-0.2.2.dist-info/METADATA
modssc-0.2.2.dist-info/WHEEL
modssc-0.2.2.dist-info/entry_points.txt
modssc-0.2.2.dist-info/licenses/LICENSE
modssc-0.2.2.dist-info/RECORD
